{
  "groups": [
    {
      "name": "站务组",
      "name_en": "FORUM AFFAIRS GROUP",
      "intro": "我们给遵纪守法的好公民颁发合法身份，分派权利！我们有全站\"官员\"的任免大权！我们手握大小版面的生杀大权！我们是全站飘的斑竹！碰到干坏事的要坚决关进小黑屋！碰到毁三观的帖子要坚决消灭干净！我们负责监督斑竹的权利，我们坚决维护广大用户的合法权益！",
      "slides": [
        {
          "text": "大大小小的版面，都由站务组管理，加入站务组，论坛江湖上的风吹草动，都逃不过你的法眼！",
          "img": "/uploads/screenshot_2018-09-20-23-25-29.jpg"
        }
      ]
    },
    {
      "name": "技术组",
      "name_en": "DEVELOPE GROUP",
      "intro": "BYR 坚强的技术后盾，新产品的研发中心。<br>我们研究 Node.js 、Python 和 PHP ，我们部署 CI 、集群和 OpenShift ，我们讨论前后端 Web 开发和折腾智能硬件，我们维护开源技术社区并和清华科大的小伙伴们交流，我们维护论坛和 BT 、开发和设计新产品，探讨一切有趣的技术话题！<br>如果你喜欢 UI 设计，也欢迎加入我们的 UI 设计研究小组，一起打造理想中的新产品！<br>希望热爱技术的小伙伴加入我们一起玩！",
      "links": [
        {
          "title": "Github",
          "url": "http://github.com/byrIo"
        },
        {
          "title": "计划中项目",
          "url": "http://wiki.byr.moe/books/byrio/page/circle-idea"
        },
        {
          "title": "BYRIO 技术社区",
          "url": "http://byrio.org"
        }
      ],
      "slides": [
        {
          "link": "http://byrio.org/soscon-18-after/"
        }
      ]
    },
    {
      "name": "美工组",
      "name_en": "DESIGN GROUP",
      "intro": "Banner？海报？台历？周边？web界面？冬夏坛服？毕业衫？新生服？<br> 对，是我们，全是我们，都是我们!<br>我们每天和设计打交道，为论坛各项活动宣传品的审美把关。只要你热爱设计追逐美学，在这里你会有一个巨大的舞台去燃烧你的小宇宙，你将收获身为一个美工人的骄傲与幸福。<br>手痒痒了？这两天北邮人正在招美工呢，要不要来试一下？",
      "links": [],
      "slides": [
        {
          "text": "<b>作品展示-BYR月历</b><br>月历由北邮人团队美工组设计，每月一期，提供不同分辨率尺寸，可用于桌面/手机屏幕壁纸。",
          "img": "/uploads/图片3.png"
        },
        {
          "text": "<b>作品展示-Banner</b><br>加入我们，你的设计将出现在日均浏览150w+的北邮人论坛及论坛app上，会有越来越多的人发现它的美！",
          "img": "/uploads/qq截图20180920150548.png"
        },
        {
          "text": "<b>作品展示-坛服</b><br>坛服是论坛的特色，加入我们，有机会参与北邮人论坛坛服夏装与冬装设计，你的作品将被穿在身上，成为北邮人的独家记忆！",
          "img": "/uploads/qq截图20180920151926.png"
        },
        {
          "text": "<b>作品展示-新生手册与周边设计</b><br>你是否还记得曾有一本新生手册，跨越千山万水，到了你的手上？<br>悄悄告诉你，参与论坛招新有机会赢取新的周边哦！",
          "img": "/uploads/qq截图20180920152301.png"
        }
      ]
    },
    {
      "name": "产品运营组",
      "name_en": "PRODUCT & OPERATION GROUP",
      "intro": "这一次，我们以产品运营组之名，重新开始。<br>我们是很”内向”的部门，可以与文宣一起探店，吃喝玩乐写攻略;可以研究产品，好的idea也有技术组来帮你实现。我们是北邮人团队最”外向”的部门，作为线下活动的组织者，作为对外的联络部门，不论是在考研交流会，还是师生羽毛球大赛，抑或是北邮人摄影大赛，都能看见我们的身影。<br>曾经的外联组，在新的学年找到了自己新的定位——产品运营组，等着全新的你加入我们！",
      "slides": []
    },
    {
      "name": "文宣组",
      "name_en": "WRITING GROUP",
      "intro": "我们用手中的笔为论坛添砖加瓦，用奇思妙想为帖子增色添彩。我们善于妙笔生花，鸿笔丽藻，急转直下。我们是论坛幕后的“键盘侠”。",
      "slides": [
        {
          "text": "我们提供一个平台，让你写你所想，让你的文思自由游荡于平平仄仄之中，让你的文段出现在大大小小的显示屏上。",
          "img": "/uploads/图片8.png"
        },
        {
          "text": "为微信公众号、官方微博提供各类文案是我们工作的日常。网页设计的文字部分也由我们负责。新生手册与考研专刊等也由我们整理。",
          "img": "/uploads/qq截图20180920155937.png"
        },
        {
          "text": "将一个一个的方块字巧妙组合，再镶在精心设计的背景布上是我们文宣青年最大的乐趣。",
          "img": "/uploads/qq截图20180920160111.png"
        }
      ]
    },
    {
      "name": "新媒体工作室",
      "name_en": "NEW MEDIA GROUP",
      "intro": "我们是驻守在北邮人论坛官方微博和微信的主页菌，我们在每一天的早安和晚安之间描绘北邮人的朝朝暮暮，这里有北邮人最关心的话题、最需要的攻略，这里有北邮人的独家记忆，也有美文和美图。<br>我们是北邮人团队新媒体组，加入我们为北邮人论坛的门户代言吧！",
      "links": [
        {
          "title": "北邮沙河校区生存攻略",
          "url": "https://mp.weixin.qq.com/mp/homepage?__biz=MjM5MDQyNjA3NQ==&hid=4&sn=0f89f8f06d8980f3652996866b5e872d&scene=18&devicetype=android-23&version=26060739&lang=zh_CN&nettype=cmnet&ascene=7&session_us=gh_de67e1f4dfc3"
        }
      ],
      "slides": [
        {
          "text": "<b>【新年盘点】再见，北邮人的2017</b><br>谁是2017年论坛第一个注册的用户？谁今年在十大宝座上坐得最久？谁是发帖之王谁又是水帖之神？让我们回顾一下北邮人一起走过的2017",
          "img": "/uploads/mmexport1536908119395.png",
          "link": "https://mp.weixin.qq.com/s/PUC_HhMQCtZ2MFTOrWixWw"
        },
        {
          "text": "在每一年官微的生日，我们都会进行组内团建，借此让新媒体这个家庭更加温暖，更加有力量！加入我们，今年的菜你来点！",
          "img": "/uploads/qq截图20180920160950.png"
        },
        {
          "text": "<b>【坛服印象】北邮人论坛和夏天的约定！</b><br>北邮人论坛坛服，是全体北邮人的共同拥有的情侣装。这是北邮人之间的小约定，约定在每一年冬夏，大家穿上坛服，和北邮谈一场无声的恋爱",
          "img": "/uploads/0-1-.jpg",
          "link": "https://mp.weixin.qq.com/s/FBBbajzFQz56FzIqUYFrlw"
        },
        {
          "text": "<b>【百家讲“坛”】北邮人论坛APP下载及使用帮助</b><br>告诉你北邮人论坛app的正确打开方式",
          "img": "/uploads/qq截图20180920161921.png",
          "link": "https://mp.weixin.qq.com/s/gRGlVnYlizNbprTFuSDpWQ"
        },
        {
          "text": "<b>主页菌在此！</b><br>此外，你还可以关注北邮人论坛官方微信公众号和官方微博 @北邮人论坛，实时了解更多信息，参与活动更是可能赢取奖品！",
          "img": "/uploads/qq截图20180920163650.png"
        }
      ]
    }
  ]
}